pyteledantic/__init__.py
pyteledantic/methods.py
pyteledantic/models.py
pyteledantic/utils.py
pyteledantic/exceptions/__init__.py
pyteledantic/exceptions/exceptions.py
tests/__init__.py
tests/conftest.py
tests/test_methods.py
pyteledantic-0.0.16.dist-info/METADATA
pyteledantic-0.0.16.dist-info/WHEEL
pyteledantic-0.0.16.dist-info/top_level.txt
pyteledantic-0.0.16.dist-info/RECORD
